fintime/__init__.py
fintime/abc.py
fintime/artists/__init__.py
fintime/artists/candlestick.py
fintime/artists/diverging_bar.py
fintime/artists/fill_between.py
fintime/artists/line.py
fintime/artists/trade_annotation.py
fintime/artists/utils.py
fintime/artists/volume.py
fintime/composites.py
fintime/config.py
fintime/mock/data.py
fintime/plot.py
fintime/ticks.py
fintime/types.py
fintime/utils.py
fintime/validation.py
fintime-0.1.6.dist-info/METADATA
fintime-0.1.6.dist-info/WHEEL
fintime-0.1.6.dist-info/RECORD
