Metadata-Version: 2.1
Name: fintime
Version: 0.1.6
Summary: Financial Time Series Plotting Libarary
Home-page: https://github.com/marcel-dehaan/fintime
License: Apache-2.0
Author: Marcel de Haan
Author-email: mdehaan35@gmail.com
Requires-Python: >=3.7,<4.0
Classifier: Development Status :: 3 - Alpha
Classifier: Intended Audience :: Developers
Classifier: License :: OSI Approved :: Apache Software License
Classifier: Programming Language :: Python :: 3
Classifier: Programming Language :: Python :: 3.7
Classifier: Programming Language :: Python :: 3.8
Classifier: Programming Language :: Python :: 3.9
Classifier: Programming Language :: Python :: 3.10
Classifier: Programming Language :: Python :: 3.11
Classifier: Programming Language :: Python :: 3.12
Classifier: Topic :: Software Development
Requires-Dist: PyYAML
Requires-Dist: fieldconfig (>=0.1.6,<0.2.0)
Requires-Dist: matplotlib (>=3.0,<4.0)
Requires-Dist: nptyping
Requires-Dist: numpy
Requires-Dist: python-dateutil
